grot/__init__.py
grot/_grot.py
grot/_id_vault.py
grot/_node_visit.py
grot/_tools.py
grot-0.2.1.dist-info/LICENSE
grot-0.2.1.dist-info/METADATA
grot-0.2.1.dist-info/WHEEL
grot-0.2.1.dist-info/top_level.txt
grot-0.2.1.dist-info/RECORD
