Metadata-Version: 2.1
Name: grot
Version: 0.2.1
Summary: Graphviz syntax wrapper. Draw graphs with pure python.
Home-page: https://gitlab.com/kamichal/grot
Author: Michal Kaczmarczyk
Author-email: michal.s.kaczmarczyk@gmail.com
Maintainer: Michal Kaczmarczyk
Maintainer-email: michal.s.kaczmarczyk@gmail.com
License: MIT license
Classifier: Development Status :: 4 - Beta
Classifier: Intended Audience :: Developers
Classifier: Intended Audience :: Education
Classifier: Intended Audience :: System Administrators
Classifier: License :: OSI Approved :: MIT License
Classifier: Natural Language :: English
Classifier: Operating System :: OS Independent
Classifier: Programming Language :: Python :: 3
Classifier: Programming Language :: Python :: 3.7
Classifier: Programming Language :: Python :: 3.8
Classifier: Programming Language :: Python :: 3.9
Classifier: Programming Language :: Python :: 3.10
Classifier: Programming Language :: Python :: Implementation :: PyPy
Classifier: Programming Language :: Python
Classifier: Topic :: Documentation
Classifier: Topic :: Multimedia :: Graphics :: Presentation
Classifier: Topic :: Multimedia :: Graphics
Classifier: Topic :: Utilities
License-File: LICENSE
Requires-Dist: graphviz (==0.20.1)
